damply/__init__.py
damply/cache_dir.py
damply/logging_config.py
damply/project.py
damply/admin/__init__.py
damply/admin/group_info.py
damply/admin/user_info.py
damply/cli/__init__.py
damply/cli/__main__.py
damply/cli/groups_table.py
damply/cli/project.py
damply/cli/whose.py
damply/cli/audit/__init__.py
damply/cli/audit/collect_audits.py
damply/cli/audit/main.py
damply/cli/audit/utils.py
damply/dmpdirs/__init__.py
damply/dmpdirs/exceptions.py
damply/plot/__init__.py
damply/plot/__main__.py
damply/plot/utils.py
damply/utils/__init__.py
damply/utils/find_readme.py
damply/utils/find_symlinks.py
damply-0.26.0.dist-info/METADATA
damply-0.26.0.dist-info/WHEEL
damply-0.26.0.dist-info/entry_points.txt
damply-0.26.0.dist-info/RECORD
