Metadata-Version: 2.4
Name: damply
Version: 0.26.0
Summary: Data Management Plan made simple.
Project-URL: homepage, https://github.com/bhklab/damply
Project-URL: repository, https://github.com/bhklab/damply
Project-URL: documentation, https://bhklab.github.io/damply/
Project-URL: changelog, https://github.com/bhklab/damply/blob/main/docs/CHANGELOG.md
Project-URL: issues, https://github.com/bhklab/damply/issues
Author-email: Jermiah Joseph <jermiahjoseph98@gmail.com>
Maintainer-email: Jermiah Joseph <jermiahjoseph98@gmail.com>
License-Expression: MIT
Keywords: damply,package,pixi,python
Classifier: License :: OSI Approved :: MIT License
Classifier: Natural Language :: English
Classifier: Operating System :: OS Independent
Classifier: Programming Language :: Python :: 3.10
Classifier: Programming Language :: Python :: 3.11
Classifier: Programming Language :: Python :: 3.12
Requires-Python: >=3.11
Requires-Dist: click<9,>=8.2
Requires-Dist: kaleido>=1.0.0
Requires-Dist: loguru<0.8,>=0.7.3
Requires-Dist: packaging>=25.0
Requires-Dist: pandas
Requires-Dist: platformdirs<5,>=4.3
Requires-Dist: plotly<7,>=6.1.0
Requires-Dist: pybytesize<0.9,>=0.8.1
Requires-Dist: rich
